slalom_explanations/__init__.py
slalom_explanations/slalom_explainer.py
slalom_explanations/slalom_helpers.py
slalom_explanations/visualizations.py
test_minimal/test_minimal.py
slalom_explanations-0.1.2.dist-info/LICENSE
slalom_explanations-0.1.2.dist-info/METADATA
slalom_explanations-0.1.2.dist-info/WHEEL
slalom_explanations-0.1.2.dist-info/top_level.txt
slalom_explanations-0.1.2.dist-info/RECORD
