Metadata-Version: 2.2
Name: slalom-explanations
Version: 0.1.2
Summary: SLALOM Explanations for transformer models.
Author-email: Tobias Leemann <tobias.leemann@uni-tuebingen.de>, Alina Fastowski <alina.fastowski@tum.de>
License:                                  Apache License
Project-URL: Homepage, https://github.com/tleemann/slalom_explanations
Project-URL: Issues, https://github.com/tleemann/slalom_explanations/issues
Classifier: Programming Language :: Python :: 3
Classifier: Operating System :: OS Independent
Requires-Python: >=3.8.1
License-File: LICENSE
Requires-Dist: torch>=2.0.0
Requires-Dist: datasets>=2.5.2
Requires-Dist: numpy>=1.23.1
Requires-Dist: matplotlib>=3.7
Requires-Dist: transformers>=4.30.0
Requires-Dist: tqdm>=4.65
Requires-Dist: scipy>=1.10.1
Requires-Dist: scikit-learn>=1.1.0
